kecleon/__init__.py
kecleon/base.py
kecleon/store.py
kecleon/jobs/__init__.py
kecleon/jobs/file.py
kecleon/jobs/raw.py
kecleon/jobs/optional/__init__.py
kecleon/jobs/optional/web.py
kecleon/jobs/optional/zip7.py
kecleon-0.0.1.dist-info/LICENSE
kecleon-0.0.1.dist-info/METADATA
kecleon-0.0.1.dist-info/WHEEL
kecleon-0.0.1.dist-info/entry_points.txt
kecleon-0.0.1.dist-info/top_level.txt
kecleon-0.0.1.dist-info/RECORD
